[
  {
    "category": "vivas",
    "pattern": "*olha para * e pronuncia as palavras 'sausabru'.",
    "matcher": {
      "source": ".*olha para .* e pronuncia as palavras 'sausabru'\\.",
      "flags": "i"
    },
    "soundPath": "Sounds/uar_Vivas/sausabru1_viva.mp3",
    "volumeRef": null
  },
  {
    "category": "vivas",
    "pattern": "*olha para * e pronuncia as palavras 'poison'.",
    "matcher": {
      "source": ".*olha para .* e pronuncia as palavras 'poison'\\.",
      "flags": "i"
    },
    "soundPath": "Sounds/uar_Vivas/sausabru1_viva.mp3",
    "volumeRef": null
  },
  {
    "category": "vivas",
    "pattern": "*olha para voc* enquanto pronuncia as palavras 'sausabru'.",
    "matcher": {
      "source": ".*olha para voc.* enquanto pronuncia as palavras 'sausabru'\\.",
      "flags": "i"
    },
    "soundPath": "Sounds/uar_Vivas/sausabru1_viva.mp3",
    "volumeRef": null
  },
  {
    "category": "vivas",
    "pattern": "*olha para voc* enquanto pronuncia as palavras 'poison'.",
    "matcher": {
      "source": ".*olha para voc.* enquanto pronuncia as palavras 'poison'\\.",
      "flags": "i"
    },
    "soundPath": "Sounds/uar_Vivas/sausabru1_viva.mp3",
    "volumeRef": null
  },
  {
    "category": "vivas",
    "pattern": "*olha para * e pronuncia as palavras 'yucandusvirr'.",
    "matcher": {
      "source": ".*olha para .* e pronuncia as palavras 'yucandusvirr'\\.",
      "flags": "i"
    },
    "soundPath": "Sounds/uar_Vivas/yucandusvirr1_viva.mp3",
    "volumeRef": null
  },
  {
    "category": "vivas",
    "pattern": "*olha para * e pronuncia as palavras 'fireball'.",
    "matcher": {
      "source": ".*olha para .* e pronuncia as palavras 'fireball'\\.",
      "flags": "i"
    },
    "soundPath": "Sounds/uar_Vivas/yucandusvirr1_viva.mp3",
    "volumeRef": null
  },
  {
    "category": "vivas",
    "pattern": "*olha para voc* enquanto pronuncia as palavras 'yucandusvirr'.",
    "matcher": {
      "source": ".*olha para voc.* enquanto pronuncia as palavras 'yucandusvirr'\\.",
      "flags": "i"
    },
    "soundPath": "Sounds/uar_Vivas/yucandusvirr1_viva.mp3",
    "volumeRef": null
  },
  {
    "category": "vivas",
    "pattern": "*olha para voc* enquanto pronuncia as palavras 'fireball'.",
    "matcher": {
      "source": ".*olha para voc.* enquanto pronuncia as palavras 'fireball'\\.",
      "flags": "i"
    },
    "soundPath": "Sounds/uar_Vivas/yucandusvirr1_viva.mp3",
    "volumeRef": null
  },
  {
    "category": "vivas",
    "pattern": "*olha para * e pronuncia as palavras 'noselacri'.",
    "matcher": {
      "source": ".*olha para .* e pronuncia as palavras 'noselacri'\\.",
      "flags": "i"
    },
    "soundPath": "Sounds/uar_Vivas/noselacri1_viva.mp3",
    "volumeRef": null
  },
  {
    "category": "vivas",
    "pattern": "*olha para * e pronuncia as palavras 'blindness'.",
    "matcher": {
      "source": ".*olha para .* e pronuncia as palavras 'blindness'\\.",
      "flags": "i"
    },
    "soundPath": "Sounds/uar_Vivas/noselacri1_viva.mp3",
    "volumeRef": null
  },
  {
    "category": "vivas",
    "pattern": "*olha para voc* enquanto pronuncia as palavras 'noselacri'.",
    "matcher": {
      "source": ".*olha para voc.* enquanto pronuncia as palavras 'noselacri'\\.",
      "flags": "i"
    },
    "soundPath": "Sounds/uar_Vivas/noselacri1_viva.mp3",
    "volumeRef": null
  },
  {
    "category": "vivas",
    "pattern": "*olha para voc* enquanto pronuncia as palavras 'blindness'.",
    "matcher": {
      "source": ".*olha para voc.* enquanto pronuncia as palavras 'blindness'\\.",
      "flags": "i"
    },
    "soundPath": "Sounds/uar_Vivas/noselacri1_viva.mp3",
    "volumeRef": null
  },
  {
    "category": "vivas",
    "pattern": "*olha para * e pronuncia as palavras 'wubaf poirubt'.",
    "matcher": {
      "source": ".*olha para .* e pronuncia as palavras 'wubaf poirubt'\\.",
      "flags": "i"
    },
    "soundPath": "Sounds/uar_Vivas/wubafpoirubt1_viva.mp3",
    "volumeRef": null
  },
  {
    "category": "vivas",
    "pattern": "*olha para * e pronuncia as palavras 'minor healing'.",
    "matcher": {
      "source": ".*olha para .* e pronuncia as palavras 'minor healing'\\.",
      "flags": "i"
    },
    "soundPath": "Sounds/uar_Vivas/wubafpoirubt1_viva.mp3",
    "volumeRef": null
  },
  {
    "category": "vivas",
    "pattern": "*olha para voc* enquanto pronuncia as palavras 'wubaf poirubt'.",
    "matcher": {
      "source": ".*olha para voc.* enquanto pronuncia as palavras 'wubaf poirubt'\\.",
      "flags": "i"
    },
    "soundPath": "Sounds/uar_Vivas/wubafpoirubt1_viva.mp3",
    "volumeRef": null
  },
  {
    "category": "vivas",
    "pattern": "*olha para voc* enquanto pronuncia as palavras 'minor healing'.",
    "matcher": {
      "source": ".*olha para voc.* enquanto pronuncia as palavras 'minor healing'\\.",
      "flags": "i"
    },
    "soundPath": "Sounds/uar_Vivas/wubafpoirubt1_viva.mp3",
    "volumeRef": null
  },
  {
    "category": "vivas",
    "pattern": "*olha para * e pronuncia as palavras 'poir'.",
    "matcher": {
      "source": ".*olha para .* e pronuncia as palavras 'poir'\\.",
      "flags": "i"
    },
    "soundPath": "Sounds/uar_Vivas/poir1_viva.mp3",
    "volumeRef": null
  },
  {
    "category": "vivas",
    "pattern": "*olha para * e pronuncia as palavras 'heal'.",
    "matcher": {
      "source": ".*olha para .* e pronuncia as palavras 'heal'\\.",
      "flags": "i"
    },
    "soundPath": "Sounds/uar_Vivas/poir1_viva.mp3",
    "volumeRef": null
  },
  {
    "category": "vivas",
    "pattern": "*olha para voc* enquanto pronuncia as palavras 'poir'.",
    "matcher": {
      "source": ".*olha para voc.* enquanto pronuncia as palavras 'poir'\\.",
      "flags": "i"
    },
    "soundPath": "Sounds/uar_Vivas/poir1_viva.mp3",
    "volumeRef": null
  },
  {
    "category": "vivas",
    "pattern": "*olha para voc* enquanto pronuncia as palavras 'heal'.",
    "matcher": {
      "source": ".*olha para voc.* enquanto pronuncia as palavras 'heal'\\.",
      "flags": "i"
    },
    "soundPath": "Sounds/uar_Vivas/poir1_viva.mp3",
    "volumeRef": null
  },
  {
    "category": "vivas",
    "pattern": "*olha para * e pronuncia as palavras 'unsoftl mgruub'.",
    "matcher": {
      "source": ".*olha para .* e pronuncia as palavras 'unsoftl mgruub'\\.",
      "flags": "i"
    },
    "soundPath": "Sounds/uar_Vivas/unsoftlmgruub1_viva.mp3",
    "volumeRef": null
  },
  {
    "category": "vivas",
    "pattern": "*olha para * e pronuncia as palavras 'energy drain'.",
    "matcher": {
      "source": ".*olha para .* e pronuncia as palavras 'energy drain'\\.",
      "flags": "i"
    },
    "soundPath": "Sounds/uar_Vivas/unsoftlmgruub1_viva.mp3",
    "volumeRef": null
  },
  {
    "category": "vivas",
    "pattern": "*olha para voc* enquanto pronuncia as palavras 'unsoftl mgruub'.",
    "matcher": {
      "source": ".*olha para voc.* enquanto pronuncia as palavras 'unsoftl mgruub'\\.",
      "flags": "i"
    },
    "soundPath": "Sounds/uar_Vivas/unsoftlmgruub1_viva.mp3",
    "volumeRef": null
  },
  {
    "category": "vivas",
    "pattern": "*olha para voc* enquanto pronuncia as palavras 'energy drain'.",
    "matcher": {
      "source": ".*olha para voc.* enquanto pronuncia as palavras 'energy drain'\\.",
      "flags": "i"
    },
    "soundPath": "Sounds/uar_Vivas/unsoftlmgruub1_viva.mp3",
    "volumeRef": null
  }
]
